castlecraft_engineer/__init__.py
castlecraft_engineer/exc.py
castlecraft_engineer/py.typed
castlecraft_engineer/abstractions/__init__.py
castlecraft_engineer/abstractions/aggregate.py
castlecraft_engineer/abstractions/command.py
castlecraft_engineer/abstractions/command_bus.py
castlecraft_engineer/abstractions/command_handler.py
castlecraft_engineer/abstractions/event.py
castlecraft_engineer/abstractions/event_bus.py
castlecraft_engineer/abstractions/event_consumer.py
castlecraft_engineer/abstractions/event_handler.py
castlecraft_engineer/abstractions/event_publisher.py
castlecraft_engineer/abstractions/event_sourced_aggregate.py
castlecraft_engineer/abstractions/event_store.py
castlecraft_engineer/abstractions/projection.py
castlecraft_engineer/abstractions/projection_store.py
castlecraft_engineer/abstractions/projector.py
castlecraft_engineer/abstractions/query.py
castlecraft_engineer/abstractions/query_bus.py
castlecraft_engineer/abstractions/query_handler.py
castlecraft_engineer/abstractions/repository.py
castlecraft_engineer/abstractions/snapshot.py
castlecraft_engineer/abstractions/snapshot_store.py
castlecraft_engineer/abstractions/specification.py
castlecraft_engineer/abstractions/translator.py
castlecraft_engineer/application/__init__.py
castlecraft_engineer/application/auth/__init__.py
castlecraft_engineer/application/auth/_base.py
castlecraft_engineer/application/auth/_bcl_mixin.py
castlecraft_engineer/application/auth/_cache_mixin.py
castlecraft_engineer/application/auth/_constants.py
castlecraft_engineer/application/auth/_jwks_mixin.py
castlecraft_engineer/application/auth/_verification_mixin.py
castlecraft_engineer/application/auth/service.py
castlecraft_engineer/authorization/__init__.py
castlecraft_engineer/authorization/base_service.py
castlecraft_engineer/authorization/default_services.py
castlecraft_engineer/authorization/permission.py
castlecraft_engineer/authorization/setup.py
castlecraft_engineer/authorization/types.py
castlecraft_engineer-0.11.0.dist-info/METADATA
castlecraft_engineer-0.11.0.dist-info/WHEEL
castlecraft_engineer-0.11.0.dist-info/entry_points.txt
castlecraft_engineer-0.11.0.dist-info/licenses/LICENSE
castlecraft_engineer-0.11.0.dist-info/RECORD
