Metadata-Version: 2.4
Name: castlecraft-engineer
Version: 0.11.0
Summary: Python framework for building robust, scalable applications with DDD, CQRS, and Event Sourcing.
Project-URL: Homepage, https://gitlab.com/castlecraft/framework/engineer
Project-URL: Documentation, https://engineer.castlecraft.in/
Project-URL: Repository, https://gitlab.com/castlecraft/framework/engineer
Project-URL: Bug Tracker, https://gitlab.com/castlecraft/framework/engineer/-/issues
Author-email: "Castlecraft Ecommerce Pvt. Ltd." <support@castlecraft.in>
License: MIT License
License-File: LICENSE
Keywords: CQRS,DDD,Event Sourcing,architecture,domain-driven design,framework,python
Classifier: Development Status :: 4 - Beta
Classifier: Intended Audience :: Developers
Classifier: License :: OSI Approved :: MIT License
Classifier: Operating System :: OS Independent
Classifier: Programming Language :: Python :: 3
Classifier: Programming Language :: Python :: 3.10
Classifier: Programming Language :: Python :: 3.11
Classifier: Programming Language :: Python :: 3.12
Classifier: Programming Language :: Python :: 3.13
Classifier: Typing :: Typed
Requires-Python: >=3.10
Requires-Dist: cryptography>=44.0.3
Requires-Dist: punq>=0.7.0
Requires-Dist: pyjwt[crypto]>=2.10.1
Requires-Dist: sqlmodel~=0.0.24
